agents/__init__.py
agents/agent_tools.py
agents/conversation_handler.py
agents/openai_agent.py
api/__init__.py
api/app_factory.py
api/endpoints.py
api/main.py
api/middleware.py
api/models.py
api/server.py
api/routes/__init__.py
api/routes/analysis.py
api/routes/configuration.py
api/routes/data.py
api/routes/datasets.py
api/routes/experiments.py
api/routes/jobs.py
api/routes/models.py
api/routes/system.py
causal/causal_discovery_engine.py
causal/discovery.py
causal/intervention.py
config/config_manager.py
data/datasets/__init__.py
data/datasets/huggingface_integration.py
data/loaders/genomics_loader.py
data/loaders/imaging_loader.py
data/loaders/molecular_loader.py
data/processors/augmentation.py
data/processors/feature_extractor.py
data/processors/image_processor.py
experimental_design/active_learning.py
explainability/__init__.py
explainability/attention_maps.py
explainability/concept_activation.py
explainability/pathway_analysis.py
losses/__init__.py
losses/causal_losses.py
losses/fusion_losses.py
models/__init__.py
models/causal/causal_vae.py
models/fusion/__init__.py
models/fusion/multimodal_transformer.py
models/graph/__init__.py
models/graph/molecular_gnn.py
models/vision/__init__.py
models/vision/cell_vit.py
openperturbation-1.1.2.dist-info/licenses/LICENSE
pipeline/__init__.py
pipeline/openperturbation_pipeline.py
training/data_modules.py
training/lightning_modules.py
training/training_losses.py
training/training_metrics.py
utils/biology_utils.py
utils/logging_config.py
utils/metrics.py
openperturbation-1.1.2.dist-info/METADATA
openperturbation-1.1.2.dist-info/WHEEL
openperturbation-1.1.2.dist-info/entry_points.txt
openperturbation-1.1.2.dist-info/top_level.txt
openperturbation-1.1.2.dist-info/RECORD
