Metadata-Version: 2.4
Name: openperturbation
Version: 1.1.2
Summary: Open-source platform for perturbation biology, causal discovery and optimal intervention design
Home-page: https://github.com/llamasearchai/OpenPerturbation
Author: Nik Jois
Author-email: Nik Jois <nikjois@llamasearch.ai>
Maintainer-email: Nik Jois <nikjois@llamasearch.ai>
License-Expression: MIT
Project-URL: Homepage, https://github.com/llamasearchai/OpenPerturbation
Project-URL: Documentation, https://llamasearchai.github.io/OpenPerturbation
Project-URL: Repository, https://github.com/llamasearchai/OpenPerturbation
Project-URL: Issues, https://github.com/llamasearchai/OpenPerturbation/issues
Project-URL: Changelog, https://github.com/llamasearchai/OpenPerturbation/blob/main/CHANGELOG.md
Keywords: perturbation-biology,causal-discovery,machine-learning,bioinformatics,genomics,intervention-design,multimodal-fusion
Classifier: Development Status :: 5 - Production/Stable
Classifier: Intended Audience :: Science/Research
Classifier: Intended Audience :: Developers
Classifier: Operating System :: OS Independent
Classifier: Programming Language :: Python :: 3
Classifier: Programming Language :: Python :: 3.10
Classifier: Programming Language :: Python :: 3.11
Classifier: Programming Language :: Python :: 3.12
Classifier: Topic :: Scientific/Engineering :: Bio-Informatics
Classifier: Topic :: Scientific/Engineering :: Artificial Intelligence
Classifier: Typing :: Typed
Requires-Python: >=3.8
License-File: LICENSE
Requires-Dist: fastapi>=0.104.0
Requires-Dist: uvicorn[standard]>=0.24.0
Requires-Dist: pydantic>=2.5.0
Requires-Dist: python-multipart>=0.0.6
Requires-Dist: aiofiles>=23.0.0
Requires-Dist: httpx>=0.25.0
Requires-Dist: omegaconf>=2.3.0
Requires-Dist: pandas>=2.0.0
Requires-Dist: numpy<2.0.0,>=1.24.0
Requires-Dist: scipy<1.12.0,>=1.10.0
Requires-Dist: scikit-learn<1.4.0,>=1.3.0
Requires-Dist: scikit-image<0.23.0,>=0.21.0
Requires-Dist: torch>=2.0.0
Requires-Dist: torchvision>=0.15.0
Requires-Dist: lightning>=2.0.0
Requires-Dist: causal-learn>=0.1.3.3
Requires-Dist: networkx>=3.0
Requires-Dist: biopython>=1.81
Requires-Dist: rdkit>=2022.9.5
Requires-Dist: Pillow>=10.0.0
Requires-Dist: opencv-python>=4.8.0
Requires-Dist: albumentations>=1.3.0
Requires-Dist: matplotlib>=3.7.0
Requires-Dist: seaborn>=0.12.0
Requires-Dist: plotly>=5.15.0
Requires-Dist: psutil>=5.9.0
Requires-Dist: tqdm>=4.65.0
Requires-Dist: joblib>=1.3.0
Provides-Extra: dev
Requires-Dist: pytest>=7.4.0; extra == "dev"
Requires-Dist: pytest-asyncio>=0.21.0; extra == "dev"
Requires-Dist: pytest-cov>=4.1.0; extra == "dev"
Requires-Dist: black>=23.9.0; extra == "dev"
Requires-Dist: mypy>=1.6.0; extra == "dev"
Requires-Dist: flake8>=6.0.0; extra == "dev"
Requires-Dist: mkdocs-material>=9.0.0; extra == "dev"
Requires-Dist: pytest-benchmark>=4.0.0; extra == "dev"
Provides-Extra: docs
Requires-Dist: mkdocs-material>=9.0.0; extra == "docs"
Provides-Extra: test
Requires-Dist: pytest>=7.4.0; extra == "test"
Requires-Dist: pytest-asyncio>=0.21.0; extra == "test"
Requires-Dist: pytest-cov>=4.1.0; extra == "test"
Dynamic: author
Dynamic: home-page
Dynamic: license-file
Dynamic: requires-python
